setup.py
RMSPYlib/__init__.py
RMSPYlib/weather.py
RMSPYlib.egg-info/PKG-INFO
RMSPYlib.egg-info/SOURCES.txt
RMSPYlib.egg-info/dependency_links.txt
RMSPYlib.egg-info/requires.txt
RMSPYlib.egg-info/top_level.txt