Metadata-Version: 2.1
Name: RMSPYlib
Version: 1.3
Summary: Derivada para uso em conversões de python para o RMS
Author: CGI
Author-email: andre.ershov@cgi.com
